setup.py
thread_genius.egg-info/PKG-INFO
thread_genius.egg-info/SOURCES.txt
thread_genius.egg-info/dependency_links.txt
thread_genius.egg-info/requires.txt
thread_genius.egg-info/top_level.txt
threadgenius/__init__.py
threadgenius/client.py
threadgenius/types.py