Metadata-Version: 1.0
Name: thread-genius
Version: 0.0.6
Summary: Thread Genius API Python Client
Home-page: https://github.com/threadgenius/thread-genius-python
Author: Andrew Shum
Author-email: andrew@threadgenius.co
License: Apache 2.0
Platform: UNKNOWN
